polymerist/__init__.py
polymerist/_version.py
polymerist/polymerist.py
polymerist/py.typed
polymerist/data/__init__.py
polymerist/genutils/__init__.py
polymerist/genutils/attrs.py
polymerist/genutils/bits.py
polymerist/genutils/containers.py
polymerist/genutils/duration.py
polymerist/genutils/filters.py
polymerist/genutils/iteration.py
polymerist/genutils/decorators/__init__.py
polymerist/genutils/decorators/classmod.py
polymerist/genutils/decorators/functional.py
polymerist/genutils/decorators/meta.py
polymerist/genutils/decorators/signatures.py
polymerist/genutils/fileutils/__init__.py
polymerist/genutils/fileutils/extensions.py
polymerist/genutils/fileutils/filetree.py
polymerist/genutils/fileutils/pathutils.py
polymerist/genutils/fileutils/jsonio/__init__.py
polymerist/genutils/fileutils/jsonio/jsonify.py
polymerist/genutils/fileutils/jsonio/serialize.py
polymerist/genutils/fileutils/jsonio/update.py
polymerist/genutils/importutils/__init__.py
polymerist/genutils/importutils/dependencies.py
polymerist/genutils/importutils/pkginspect.py
polymerist/genutils/importutils/pkgiter.py
polymerist/genutils/importutils/pyimports.py
polymerist/genutils/logutils/IOHandlers.py
polymerist/genutils/logutils/__init__.py
polymerist/genutils/logutils/timestamps.py
polymerist/genutils/sequences/__init__.py
polymerist/genutils/sequences/seqops.py
polymerist/genutils/sequences/discernment/__init__.py
polymerist/genutils/sequences/discernment/enumeration.py
polymerist/genutils/sequences/discernment/examples.py
polymerist/genutils/sequences/discernment/inventory.py
polymerist/genutils/sequences/discernment/strategies.py
polymerist/genutils/sequences/similarity/__init__.py
polymerist/genutils/sequences/similarity/distances.py
polymerist/genutils/sequences/similarity/edits.py
polymerist/genutils/textual/__init__.py
polymerist/genutils/textual/casing.py
polymerist/genutils/textual/delimiters.py
polymerist/genutils/textual/encoding.py
polymerist/genutils/textual/interpolation.py
polymerist-1.0.1.dist-info/licenses/LICENSE
polymerist-1.0.1.dist-info/METADATA
polymerist-1.0.1.dist-info/WHEEL
polymerist-1.0.1.dist-info/top_level.txt
polymerist-1.0.1.dist-info/RECORD
