Metadata-Version: 2.4
Name: polymerist
Version: 1.0.1
Summary: A unified set of tools for setting up general organic polymer systems for MD within the OpenFF framework
Author-email: Timotej Bernat <timotej.bernat@colorado.edu>
License: MIT
Project-URL: Homepage, https://polymerist.readthedocs.io/en/docs/
Project-URL: Documentation, https://polymerist.readthedocs.io/en/docs/
Project-URL: Download, https://pypi.org/project/polymerist/
Project-URL: Source, https://github.com/timbernat/polymerist
Project-URL: Issues, https://github.com/timbernat/polymerist/issues
Project-URL: Examples, https://github.com/timbernat/polymerist_examples
Classifier: License :: OSI Approved :: MIT License
Classifier: Programming Language :: Python :: 3
Requires-Python: ~=3.11
License-File: LICENSE
Requires-Dist: importlib-resources
Requires-Dist: numpy<2.0.0
Requires-Dist: scipy
Requires-Dist: pandas
Requires-Dist: rich
Requires-Dist: pillow
Requires-Dist: matplotlib
Requires-Dist: anytree
Requires-Dist: networkx
Requires-Dist: rdkit
Requires-Dist: openmm
Requires-Dist: lammps<=2024.08.29
Requires-Dist: mdtraj
Provides-Extra: test
Requires-Dist: pytest>=6.1.2; extra == "test"
Requires-Dist: pytest-runner; extra == "test"
Requires-Dist: pytest-cov; extra == "test"
Requires-Dist: codecov; extra == "test"
Provides-Extra: interactive
Requires-Dist: jupyterlab; extra == "interactive"
Requires-Dist: ipywidgets==8.0.4; extra == "interactive"
Requires-Dist: nglview==3.0.6; extra == "interactive"
Requires-Dist: py3Dmol; extra == "interactive"
Provides-Extra: chemdb
Requires-Dist: cirpy; extra == "chemdb"
Requires-Dist: pubchempy; extra == "chemdb"
Requires-Dist: chemspipy; extra == "chemdb"
Dynamic: license-file
